grimoirelab/__init__.py
grimoirelab/_version.py
grimoirelab/grimoirelab.py
grimoirelab-1.19.0.dist-info/LICENSE
grimoirelab-1.19.0.dist-info/METADATA
grimoirelab-1.19.0.dist-info/WHEEL
grimoirelab-1.19.0.dist-info/entry_points.txt
grimoirelab-1.19.0.dist-info/RECORD
