Metadata-Version: 2.1
Name: grimoirelab
Version: 1.19.0
Summary: Tool set for software development analytics
Home-page: https://chaoss.github.io/grimoirelab/
License: GPL-3.0+
Keywords: development,grimoirelab
Author: GrimoireLab Developers
Requires-Python: >=3.10,<4.0
Classifier: Development Status :: 5 - Production/Stable
Classifier: Intended Audience :: Developers
Classifier: License :: OSI Approved :: GNU General Public License v3 or later (GPLv3+)
Classifier: Programming Language :: Python :: 3
Classifier: Programming Language :: Python :: 3.10
Classifier: Programming Language :: Python :: 3.11
Classifier: Topic :: Software Development
Requires-Dist: asgiref (==3.11.0)
Requires-Dist: astroid (==4.0.3)
Requires-Dist: async-timeout (==5.0.1)
Requires-Dist: bandit (==1.9.3)
Requires-Dist: beautifulsoup4 (==4.14.3)
Requires-Dist: cereslib (==1.1.6)
Requires-Dist: certifi (==2026.1.4)
Requires-Dist: cffi (==2.0.0)
Requires-Dist: charset-normalizer (==3.4.4)
Requires-Dist: click (==8.3.1)
Requires-Dist: cloc (==0.2.5)
Requires-Dist: colored (==2.3.1)
Requires-Dist: colorlog (==6.10.1)
Requires-Dist: croniter (==6.0.0)
Requires-Dist: cryptography (==46.0.3)
Requires-Dist: dill (==0.4.1)
Requires-Dist: django (==5.2.10)
Requires-Dist: django-cors-headers (==4.9.0)
Requires-Dist: django-graphql-jwt (==0.4.0)
Requires-Dist: django-rq (==3.2.2)
Requires-Dist: django-storages (==1.14.6)
Requires-Dist: django-treebeard (==4.8.0)
Requires-Dist: dulwich (==0.22.8)
Requires-Dist: events (==0.5)
Requires-Dist: execnet (==2.1.2)
Requires-Dist: feedparser (==6.0.12)
Requires-Dist: file-read-backwards (==3.2.0)
Requires-Dist: flake8 (==7.3.0)
Requires-Dist: geographiclib (==2.1)
Requires-Dist: geopy (==2.4.1)
Requires-Dist: google-api-core (==2.29.0)
Requires-Dist: google-auth (==2.47.0)
Requires-Dist: google-cloud-core (==2.5.0)
Requires-Dist: google-cloud-storage (==3.8.0)
Requires-Dist: google-crc32c (==1.8.0)
Requires-Dist: google-resumable-media (==2.8.0)
Requires-Dist: googleapis-common-protos (==1.72.0)
Requires-Dist: graal (==1.2.6)
Requires-Dist: graphene (==3.4.3)
Requires-Dist: graphene-django (==3.2.3)
Requires-Dist: graphql-core (==3.2.7)
Requires-Dist: graphql-relay (==3.2.0)
Requires-Dist: grimoire-elk (==1.7.0)
Requires-Dist: grimoirelab-panels (==1.2.0)
Requires-Dist: grimoirelab-toolkit (==1.2.5)
Requires-Dist: grpcio (==1.76.0)
Requires-Dist: idna (==3.11)
Requires-Dist: isort (==7.0.0)
Requires-Dist: jinja2 (==3.1.6)
Requires-Dist: kidash (==1.1.6)
Requires-Dist: lizard (==1.20.0)
Requires-Dist: markdown-it-py (==2.2.0)
Requires-Dist: markupsafe (==3.0.3)
Requires-Dist: mccabe (==0.7.0)
Requires-Dist: mdurl (==0.1.2)
Requires-Dist: mysqlclient (==2.2.7)
Requires-Dist: networkx (==3.4.2)
Requires-Dist: numpy (==2.2.6)
Requires-Dist: opensearch-protobufs (==0.19.0)
Requires-Dist: opensearch-py (==3.1.0)
Requires-Dist: packaging (==25.0)
Requires-Dist: pandas (==2.3.3)
Requires-Dist: pathspec (==1.0.3)
Requires-Dist: patsy (==1.0.2)
Requires-Dist: perceval (==1.4.5)
Requires-Dist: perceval-mozilla (==1.2.6)
Requires-Dist: perceval-opnfv (==1.1.6)
Requires-Dist: perceval-puppet (==1.1.6)
Requires-Dist: perceval-weblate (==1.1.6)
Requires-Dist: platformdirs (==4.5.1)
Requires-Dist: promise (==2.3)
Requires-Dist: proto-plus (==1.27.0)
Requires-Dist: protobuf (==6.33.4)
Requires-Dist: pyasn1 (==0.6.2)
Requires-Dist: pyasn1-modules (==0.4.2)
Requires-Dist: pycodestyle (==2.14.0)
Requires-Dist: pycparser (==2.23)
Requires-Dist: pydot (==4.0.1)
Requires-Dist: pyflakes (==3.4.0)
Requires-Dist: pygments (==2.19.2)
Requires-Dist: pyjwt (==2.10.1)
Requires-Dist: pylint (==4.0.4)
Requires-Dist: pyparsing (==3.3.2)
Requires-Dist: python-dateutil (==2.9.0.post0)
Requires-Dist: pytz (==2025.2)
Requires-Dist: pyyaml (==6.0.3)
Requires-Dist: redis (==7.1.0)
Requires-Dist: requests (==2.32.5)
Requires-Dist: rich (==14.2.0)
Requires-Dist: rq (==2.6.1)
Requires-Dist: rsa (==4.9.1)
Requires-Dist: scipy (==1.15.3)
Requires-Dist: sgmllib3k (==1.0.0)
Requires-Dist: sgqlc (==16.5)
Requires-Dist: sirmordred (==1.2.6)
Requires-Dist: six (==1.17.0)
Requires-Dist: sortinghat (==1.13.0)
Requires-Dist: soupsieve (==2.8.3)
Requires-Dist: sqlparse (==0.5.5)
Requires-Dist: statsmodels (==0.14.6)
Requires-Dist: stevedore (==5.6.0)
Requires-Dist: text-unidecode (==1.3)
Requires-Dist: tomli (==2.4.0)
Requires-Dist: tomlkit (==0.14.0)
Requires-Dist: typing-extensions (==4.15.0)
Requires-Dist: tzdata (==2025.3)
Requires-Dist: urllib3 (==2.6.3)
Requires-Dist: uwsgi (==2.0.31)
Project-URL: Bug Tracker, https://github.com/chaoss/grimoirelab/issues
Project-URL: Repository, https://github.com/chaoss/grimoirelab
